pyview/__init__.py
pyview/mvc.py
pyview/widgets.py
pyview-1.1.0.dist-info/METADATA
pyview-1.1.0.dist-info/WHEEL
pyview-1.1.0.dist-info/top_level.txt
pyview-1.1.0.dist-info/RECORD
